atmm/__init__.py
atmm-0.0.2.dist-info/LICENSE
atmm-0.0.2.dist-info/METADATA
atmm-0.0.2.dist-info/WHEEL
atmm-0.0.2.dist-info/top_level.txt
atmm-0.0.2.dist-info/RECORD
