Metadata-Version: 2.1
Name: atmm
Version: 0.0.2
Summary: Animation Time Manager for Manim
Home-page: https://github.com/chunribu/atmm
Author: Jian Jiang
Author-email: jianjiang.bio@gmail.com
License: MIT
Keywords: Animation Time Manager Manim
Classifier: Operating System :: POSIX :: Linux
Classifier: Operating System :: MacOS :: MacOS X
Classifier: License :: OSI Approved :: MIT License
Classifier: Programming Language :: Python :: 3
License-File: LICENSE
